{
    "format_version": "1.14",
    "minecraft:npc_dialogue": {
        "scenes": [
            {
                "buttons": [
                    {
                        "commands": [
                            "/execute @initiator ~ ~ ~ scoreboard players set @s task_player_num 2 ",
                            "/execute @initiator ~ ~ ~ dialogue open @e[type=npc, r=6, c=1] @s task_8_room_select"
                        ],
                        "name": "Klar"
                    },
                    {
                        "commands": [],
                        "name": "Nein, danke"
                    }
                ],
                "npc_name": "Navigator",
                "on_close_commands": [],
                "on_open_commands": [],
                "scene_tag": "task_8_nav_npc",
                "text": "Hallo! Willst du die vorläufige Version des neuen städtischen Sicherheitssystems ausprobieren? Dies ist eine Aufgabe für zwei Spieler, bei der einer von euch den Agenten codiert und der andere gut aufpasst und für den Coder die Augen offen hält. Diese Aufgabe ist für den Aufpasser. Möchtest du der Aufpasser sein?"
            },
            {
                "buttons": [
                    {
                        "commands": [
                            "/execute @initiator ~ ~ ~ scoreboard players set @s task_player_num 1 ",
                            "/execute @initiator ~ ~ ~ dialogue open @e[type=npc, r=6, c=1] @s task_8_room_select_driver"
                        ],
                        "name": "Klar"
                    },
                    {
                        "commands": [],
                        "name": "Nein, danke"
                    }
                ],
                "npc_name": "Fahrer",
                "on_close_commands": [],
                "on_open_commands": [],
                "scene_tag": "task_8_dri_npc",
                "text": "Hallo! Möchtest du die vorläufige Version des neuen städtischen Sicherheitssystems ausprobieren? Dies ist eine Aufgabe für zwei Spieler, bei der einer von euch den Agenten codiert und der andere gut aufpasst und für den Coder die Augen offen hält. Diese Aufgabe ist für den Coder. Möchtest du der Coder sein?"
            },
            {
                "buttons": [
                    {
                        "commands": [
                            "/execute @initiator ~ ~ ~ scoreboard players set @s task_room_num 1 ",
                            "/execute @initiator ~ ~ ~ function task8/start_blocks"
                        ],
                        "name": "Room 1"
                    },
                    {
                        "commands": [
                            "/execute @initiator ~ ~ ~ scoreboard players set @s task_room_num 2 ",
                            "/execute @initiator ~ ~ ~ function task8/start_blocks"
                        ],
                        "name": "Room 2"
                    },
                    {
                        "commands": [
                            "/execute @initiator ~ ~ ~ scoreboard players set @s task_room_num 3 ",
                            "/execute @initiator ~ ~ ~ function task8/start_blocks"
                        ],
                        "name": "Room 3"
                    },
                    {
                        "commands": [
                            "/execute @initiator ~ ~ ~ scoreboard players set @s task_room_num 4 ",
                            "/execute @initiator ~ ~ ~ function task8/start_blocks"
                        ],
                        "name": "Room 4"
                    },
                    {
                        "commands": [
                            "/execute @initiator ~ ~ ~ scoreboard players set @s task_room_num 5 ",
                            "/execute @initiator ~ ~ ~ function task8/start_blocks"
                        ],
                        "name": "Room 5"
                    },
                    {
                        "commands": [
                            "/execute @initiator ~ ~ ~ scoreboard players set @s task_room_num 6 ",
                            "/execute @initiator ~ ~ ~ function task8/start_blocks"
                        ],
                        "name": "Room 6"
                    }
                ],
                "npc_name": "Navigator",
                "on_close_commands": [],
                "on_open_commands": [],
                "scene_tag": "task_8_room_select",
                "text": "Wähle einen Raum aus, in dem du teilnehmen möchtest. Es gibt 6 Räume für diese Aufgabe und jeder ist genau gleich.\nAchte darauf, dass du den gleichen wie dein Partner wählst!"
            },
            {
                "buttons": [
                    {
                        "commands": [
                            "/execute @initiator ~ ~ ~ function task8/start_blocks"
                        ],
                        "name": "Blocks"
                    },
                    {
                        "commands": [
                            "/execute @initiator ~ ~ ~ function task8/start_python"
                        ],
                        "name": "Python"
                    }
                ],
                "npc_name": "Navigator",
                "on_close_commands": [],
                "on_open_commands": [],
                "scene_tag": "task_8_lang",
                "text": "Möchtest du mit Blocks oder Python programmieren?"
            },
            {
                "buttons": [
                    {
                        "commands": [
                            "/execute @initiator ~ ~ ~ scoreboard players set @s task_room_num 1 ",
                            "/execute @initiator ~ ~ ~ dialogue open @e[type=npc, r=6, c=1] @s task_8_lang"
                        ],
                        "name": "Room 1"
                    },
                    {
                        "commands": [
                            "/execute @initiator ~ ~ ~ scoreboard players set @s task_room_num 2 ",
                            "/execute @initiator ~ ~ ~ dialogue open @e[type=npc, r=6, c=1] @s task_8_lang"
                        ],
                        "name": "Room 2"
                    },
                    {
                        "commands": [
                            "/execute @initiator ~ ~ ~ scoreboard players set @s task_room_num 3 ",
                            "/execute @initiator ~ ~ ~ dialogue open @e[type=npc, r=6, c=1] @s task_8_lang"
                        ],
                        "name": "Room 3"
                    },
                    {
                        "commands": [
                            "/execute @initiator ~ ~ ~ scoreboard players set @s task_room_num 4 ",
                            "/execute @initiator ~ ~ ~ dialogue open @e[type=npc, r=6, c=1] @s task_8_lang"
                        ],
                        "name": "Room 4"
                    },
                    {
                        "commands": [
                            "/execute @initiator ~ ~ ~ scoreboard players set @s task_room_num 5 ",
                            "/execute @initiator ~ ~ ~ dialogue open @e[type=npc, r=6, c=1] @s task_8_lang"
                        ],
                        "name": "Room 5"
                    },
                    {
                        "commands": [
                            "/execute @initiator ~ ~ ~ scoreboard players set @s task_room_num 6 ",
                            "/execute @initiator ~ ~ ~ dialogue open @e[type=npc, r=6, c=1] @s task_8_lang"
                        ],
                        "name": "Room 6"
                    }
                ],
                "npc_name": "Fahrer",
                "on_close_commands": [],
                "on_open_commands": [],
                "scene_tag": "task_8_room_select_driver",
                "text": "Wähle einen Raum aus, in dem du teilnehmen möchtest. Es gibt 6 Räume für diese Aufgabe und jeder ist genau gleich. Achte darauf, dass du den gleichen wie dein Partner wählst!"
            }
        ]
    }
}